{
    "version": "5.1.0",
    "description": "Update your software in 2 clicks. Stay away from malware.",
    "homepage": "https://www.adlice.com/ucheck/",
    "license": {
        "identifier": "Freeware",
        "url": "https://www.adlice.com/docs/ucheck/terms-of-use/"
    },
    "architecture": {
        "64bit": {
            "url": "https://download.adlice.com/api?action=download&app=ucheck&type=x64#/UCheck_portable64.exe",
            "hash": "f9f2112fd01a48ece028a3df26d5f3a2e143c262e7aa2afbedb8ef4a9e11cf61",
            "bin": "UCheck_portable64.exe",
            "shortcuts": [
                [
                    "UCheck_portable64.exe",
                    "UCheck"
                ]
            ]
        },
        "32bit": {
            "url": "https://download.adlice.com/api?action=download&app=ucheck&type=x86#/UCheck_portable32.exe",
            "hash": "a4cf7805b673f6c17f6bb43e3b733cdfb62cec75a18f1e4c7de4347168abbfeb",
            "bin": "UCheck_portable32.exe",
            "shortcuts": [
                [
                    "UCheck_portable32.exe",
                    "UCheck"
                ]
            ]
        }
    },
    "checkver": {
        "url": "https://download.adlice.com/UCheck/Changelog.txt",
        "regex": "V([\\d.]+)"
    },
    "autoupdate": {
        "architecture": {
            "64bit": {
                "url": "https://download.adlice.com/api?action=download&app=ucheck&type=x64#/UCheck_portable64.exe"
            },
            "32bit": {
                "url": "https://download.adlice.com/api?action=download&app=ucheck&type=x86#/UCheck_portable32.exe"
            }
        }
    }
}
